LICENSE
MANIFEST.in
README.rst
setup.py
django_powerdns_dnssec.egg-info/PKG-INFO
django_powerdns_dnssec.egg-info/SOURCES.txt
django_powerdns_dnssec.egg-info/dependency_links.txt
django_powerdns_dnssec.egg-info/not-zip-safe
django_powerdns_dnssec.egg-info/requires.txt
django_powerdns_dnssec.egg-info/top_level.txt
powerdns/__init__.py
powerdns/admin.py
powerdns/models.py
powerdns/routers.py
powerdns/locale/en/LC_MESSAGES/django.mo
powerdns/locale/en/LC_MESSAGES/django.po
powerdns/locale/pl/LC_MESSAGES/django.mo
powerdns/locale/pl/LC_MESSAGES/django.po
powerdns/migrations/0001_initial.py
powerdns/migrations/0002_dnssec_models.py
powerdns/migrations/0003_timetrackable_models.py
powerdns/migrations/0004_auto__add_field_record_number.py
powerdns/migrations/__init__.py